{"SURVIVAL":{"potions":"[]","armorContents":{},"inventoryContents":{"0":{"==":"org.bukkit.inventory.ItemStack","type":"ARROW","meta":{"==":"ItemMeta","meta-type":"UNSPECIFIC","display-name":"§7SHIFT + §6Right click to go back to last checkpoint"}},"1":{"==":"org.bukkit.inventory.ItemStack","type":"BONE","meta":{"==":"ItemMeta","meta-type":"UNSPECIFIC","display-name":"§7SHIFT + §6Right click to toggle visibility"}},"2":{"==":"org.bukkit.inventory.ItemStack","type":"SAPLING","meta":{"==":"ItemMeta","meta-type":"UNSPECIFIC","display-name":"§7SHIFT + §6Right click to leave course"}},"3":{"==":"org.bukkit.inventory.ItemStack","type":"ENDER_PEARL"},"4":{"==":"org.bukkit.inventory.ItemStack","type":"WATCH","meta":{"==":"ItemMeta","meta-type":"UNSPECIFIC","display-name":"§2Humblex Menu","lore":["§6ArenaPVP - §2Online","§6Skyblock - §2Online","§6FFA      - §2Online","§6SG       - §2Online","§6factions - §4Offline","§6Skywars  - §2Online"]}}},"enderChestContents":{},"stats":{"ex":"3.6703997","ma":"300","fl":"20","el":"0","xp":"0.0","hp":"20","txp":"0","ft":"-20","sa":"3.0","fd":"0.233632","ra":"300"}}}