{"SURVIVAL":{"armorContents":{"0":{"==":"org.bukkit.inventory.ItemStack","type":"DIAMOND_BOOTS","damage":323,"meta":{"==":"ItemMeta","meta-type":"UNSPECIFIC","enchants":{"PROTECTION_ENVIRONMENTAL":4,"DURABILITY":3,"PROTECTION_FALL":4},"repair-cost":7}},"1":{"==":"org.bukkit.inventory.ItemStack","type":"DIAMOND_LEGGINGS","damage":320,"meta":{"==":"ItemMeta","meta-type":"UNSPECIFIC","enchants":{"PROTECTION_ENVIRONMENTAL":4,"DURABILITY":3},"repair-cost":3}},"2":{"==":"org.bukkit.inventory.ItemStack","type":"DIAMOND_CHESTPLATE","damage":323,"meta":{"==":"ItemMeta","meta-type":"UNSPECIFIC","enchants":{"PROTECTION_ENVIRONMENTAL":4,"DURABILITY":3},"repair-cost":3}},"3":{"==":"org.bukkit.inventory.ItemStack","type":"DIAMOND_HELMET","damage":290,"meta":{"==":"ItemMeta","meta-type":"UNSPECIFIC","enchants":{"PROTECTION_ENVIRONMENTAL":4,"DURABILITY":3},"repair-cost":3}}},"inventoryContents":{"33":{"==":"org.bukkit.inventory.ItemStack","type":"POTION","damage":8226},"34":{"==":"org.bukkit.inventory.ItemStack","type":"POTION","damage":8226},"35":{"==":"org.bukkit.inventory.ItemStack","type":"POTION","damage":8226},"27":{"==":"org.bukkit.inventory.ItemStack","type":"POTION","damage":8226},"29":{"==":"org.bukkit.inventory.ItemStack","type":"POTION","damage":8226},"0":{"==":"org.bukkit.inventory.ItemStack","type":"DIAMOND_SWORD","meta":{"==":"ItemMeta","meta-type":"UNSPECIFIC","enchants":{"DAMAGE_ALL":1,"FIRE_ASPECT":2,"DURABILITY":3},"repair-cost":7}},"1":{"==":"org.bukkit.inventory.ItemStack","type":"GOLDEN_APPLE","damage":1,"amount":59},"2":{"==":"org.bukkit.inventory.ItemStack","type":"DIAMOND_HELMET","meta":{"==":"ItemMeta","meta-type":"UNSPECIFIC","enchants":{"PROTECTION_ENVIRONMENTAL":5,"DURABILITY":4},"repair-cost":3}},"3":{"==":"org.bukkit.inventory.ItemStack","type":"DIAMOND_CHESTPLATE","meta":{"==":"ItemMeta","meta-type":"UNSPECIFIC","enchants":{"PROTECTION_ENVIRONMENTAL":5,"DURABILITY":4},"repair-cost":3}},"4":{"==":"org.bukkit.inventory.ItemStack","type":"DIAMOND_LEGGINGS","meta":{"==":"ItemMeta","meta-type":"UNSPECIFIC","enchants":{"PROTECTION_ENVIRONMENTAL":5,"DURABILITY":4},"repair-cost":3}},"5":{"==":"org.bukkit.inventory.ItemStack","type":"DIAMOND_BOOTS","meta":{"==":"ItemMeta","meta-type":"UNSPECIFIC","enchants":{"PROTECTION_ENVIRONMENTAL":5,"DURABILITY":4},"repair-cost":3}},"6":{"==":"org.bukkit.inventory.ItemStack","type":"GLASS_BOTTLE"},"7":{"==":"org.bukkit.inventory.ItemStack","type":"POTION","damage":8265},"8":{"==":"org.bukkit.inventory.ItemStack","type":"GLASS_BOTTLE"},"30":{"==":"org.bukkit.inventory.ItemStack","type":"POTION","damage":8226},"31":{"==":"org.bukkit.inventory.ItemStack","type":"POTION","damage":8226},"32":{"==":"org.bukkit.inventory.ItemStack","type":"POTION","damage":8226}},"potions":"[{\"pa\":1,\"pt\":1,\"pd\":1157},{\"pa\":0,\"pt\":5,\"pd\":7016},{\"pa\":0,\"pt\":22,\"pd\":2311},{\"pa\":4,\"pt\":10,\"pd\":511},{\"pa\":0,\"pt\":11,\"pd\":5911},{\"pa\":0,\"pt\":12,\"pd\":5911}]","enderChestContents":{},"stats":{"ex":"2.4590085","ma":"300","fl":"20","el":"0","xp":"0.0","hp":"14","txp":"0","sa":"17.0","ft":"-20","fd":"0.0","ra":"300"}}}