{"SURVIVAL":{"potions":"[]","inventoryContents":{"22":{"==":"org.bukkit.inventory.ItemStack","type":"POTION","damage":16421},"23":{"==":"org.bukkit.inventory.ItemStack","type":"POTION","damage":8226},"24":{"==":"org.bukkit.inventory.ItemStack","type":"POTION","damage":16421},"25":{"==":"org.bukkit.inventory.ItemStack","type":"POTION","damage":16421},"26":{"==":"org.bukkit.inventory.ItemStack","type":"POTION","damage":8226},"27":{"==":"org.bukkit.inventory.ItemStack","type":"POTION","damage":16421},"28":{"==":"org.bukkit.inventory.ItemStack","type":"POTION","damage":16421},"29":{"==":"org.bukkit.inventory.ItemStack","type":"POTION","damage":16421},"30":{"==":"org.bukkit.inventory.ItemStack","type":"POTION","damage":16421},"31":{"==":"org.bukkit.inventory.ItemStack","type":"POTION","damage":16421},"10":{"==":"org.bukkit.inventory.ItemStack","type":"POTION","damage":16421},"32":{"==":"org.bukkit.inventory.ItemStack","type":"POTION","damage":16421},"11":{"==":"org.bukkit.inventory.ItemStack","type":"POTION","damage":16421},"33":{"==":"org.bukkit.inventory.ItemStack","type":"POTION","damage":16421},"12":{"==":"org.bukkit.inventory.ItemStack","type":"POTION","damage":16421},"34":{"==":"org.bukkit.inventory.ItemStack","type":"ENDER_PEARL","amount":16},"13":{"==":"org.bukkit.inventory.ItemStack","type":"COOKED_BEEF","amount":62},"35":{"==":"org.bukkit.inventory.ItemStack","type":"POTION","damage":16421},"14":{"==":"org.bukkit.inventory.ItemStack","type":"POTION","damage":16421},"15":{"==":"org.bukkit.inventory.ItemStack","type":"POTION","damage":16421},"0":{"==":"org.bukkit.inventory.ItemStack","type":"BOOK","meta":{"==":"ItemMeta","meta-type":"UNSPECIFIC","display-name":"§2Set custom hotbar","lore":["§7Click to set custom hotbar."]}},"1":{"==":"org.bukkit.inventory.ItemStack","type":"DIAMOND_SWORD","meta":{"==":"ItemMeta","meta-type":"UNSPECIFIC","display-name":"§9Ranked","lore":["§7Click to play ranked matches."]}},"2":{"==":"org.bukkit.inventory.ItemStack","type":"WOOD_SWORD","meta":{"==":"ItemMeta","meta-type":"UNSPECIFIC","display-name":"§6UnRanked","lore":["§7Click to play unranked matches."]}},"3":{"==":"org.bukkit.inventory.ItemStack","type":"GOLD_INGOT","meta":{"==":"ItemMeta","meta-type":"UNSPECIFIC","display-name":"§eDuel accept","lore":["§7Accept duel."]}},"4":{"==":"org.bukkit.inventory.ItemStack","type":"GOLDEN_CARROT","meta":{"==":"ItemMeta","meta-type":"UNSPECIFIC","display-name":"§bUHC Meetup","lore":["§7Click to play UHC Meetup"]}},"5":{"==":"org.bukkit.inventory.ItemStack","type":"POTION","damage":16421},"6":{"==":"org.bukkit.inventory.ItemStack","type":"COOKED_BEEF","amount":60},"7":{"==":"org.bukkit.inventory.ItemStack","type":"NETHER_STAR","meta":{"==":"ItemMeta","meta-type":"UNSPECIFIC","display-name":"§5Party","lore":["§7Click to create a party"]}},"8":{"==":"org.bukkit.inventory.ItemStack","type":"REDSTONE_TORCH_ON","meta":{"==":"ItemMeta","meta-type":"UNSPECIFIC","display-name":"§8Options","lore":["§7Click to set options."]}},"9":{"==":"org.bukkit.inventory.ItemStack","type":"DIAMOND_SWORD","damage":7,"meta":{"==":"ItemMeta","meta-type":"UNSPECIFIC","enchants":{"DAMAGE_ALL":1,"FIRE_ASPECT":2,"DURABILITY":3},"repair-cost":7}},"21":{"==":"org.bukkit.inventory.ItemStack","type":"POTION","damage":16421}},"enderChestContents":{},"armorContents":{},"stats":{"ex":"3.1038964","ma":"300","fl":"20","el":"0","xp":"0.0","hp":"20","txp":"0","ft":"-20","fd":"0.0","sa":"10.8","ra":"300"}}}