{"SURVIVAL":{"inventoryContents":{"0":{"==":"org.bukkit.inventory.ItemStack","type":"WATCH","meta":{"==":"ItemMeta","meta-type":"UNSPECIFIC","display-name":"§d§lVote","lore":["§7Click to vote for the arena settings"]}},"4":{"==":"org.bukkit.inventory.ItemStack","type":"SKULL_ITEM","damage":3,"meta":{"==":"ItemMeta","meta-type":"SKULL","display-name":"§bProfile","lore":["§7Click to view your profile!"]}},"7":{"==":"org.bukkit.inventory.ItemStack","type":"CHEST","meta":{"==":"ItemMeta","meta-type":"TILE_ENTITY","display-name":"§bInventory","blockMaterial":"CHEST"}},"8":{"==":"org.bukkit.inventory.ItemStack","type":"MAGMA_CREAM","meta":{"==":"ItemMeta","meta-type":"UNSPECIFIC","display-name":"§cQuit","lore":["§7Click to quit the game!"]}}},"armorContents":{},"potions":"[]","enderChestContents":{},"stats":{"ex":"0.42300004","ma":"300","fl":"20","el":"0","hp":"20","xp":"0.0","txp":"0","fd":"0.0","ft":"-20","sa":"5.0","ra":"300"}}}