{"SURVIVAL":{"potions":"[{\"pa\":0,\"pt\":1,\"pd\":545},{\"pa\":0,\"pt\":22,\"pd\":927},{\"pa\":3,\"pt\":14,\"pd\":91855}]","inventoryContents":{"22":{"==":"org.bukkit.inventory.ItemStack","type":"COOKED_BEEF","amount":5},"23":{"==":"org.bukkit.inventory.ItemStack","type":"EGG","amount":64},"24":{"==":"org.bukkit.inventory.ItemStack","type":"STONE","amount":32},"26":{"==":"org.bukkit.inventory.ItemStack","type":"WOOD","amount":64},"27":{"==":"org.bukkit.inventory.ItemStack","type":"BREAD","amount":3},"28":{"==":"org.bukkit.inventory.ItemStack","type":"DIRT","amount":32},"29":{"==":"org.bukkit.inventory.ItemStack","type":"IRON_HELMET"},"30":{"==":"org.bukkit.inventory.ItemStack","type":"STONE","amount":64},"31":{"==":"org.bukkit.inventory.ItemStack","type":"ARROW","amount":63},"10":{"==":"org.bukkit.inventory.ItemStack","type":"GOLD_LEGGINGS"},"32":{"==":"org.bukkit.inventory.ItemStack","type":"GRILLED_PORK","amount":32},"11":{"==":"org.bukkit.inventory.ItemStack","type":"GOLD_CHESTPLATE"},"33":{"==":"org.bukkit.inventory.ItemStack","type":"CHAINMAIL_BOOTS"},"12":{"==":"org.bukkit.inventory.ItemStack","type":"CHAINMAIL_CHESTPLATE","meta":{"==":"ItemMeta","meta-type":"UNSPECIFIC","enchants":{"PROTECTION_EXPLOSIONS":3}}},"13":{"==":"org.bukkit.inventory.ItemStack","type":"IRON_HELMET"},"35":{"==":"org.bukkit.inventory.ItemStack","type":"SNOW_BALL","amount":16},"14":{"==":"org.bukkit.inventory.ItemStack","type":"DIAMOND_LEGGINGS"},"15":{"==":"org.bukkit.inventory.ItemStack","type":"DIAMOND_BOOTS"},"18":{"==":"org.bukkit.inventory.ItemStack","type":"REDSTONE","amount":32},"19":{"==":"org.bukkit.inventory.ItemStack","type":"WOOD","damage":5,"amount":30},"0":{"==":"org.bukkit.inventory.ItemStack","type":"STONE_SWORD"},"1":{"==":"org.bukkit.inventory.ItemStack","type":"POTION","damage":16460},"2":{"==":"org.bukkit.inventory.ItemStack","type":"POTION","damage":16453},"3":{"==":"org.bukkit.inventory.ItemStack","type":"FISHING_ROD","meta":{"==":"ItemMeta","meta-type":"UNSPECIFIC","enchants":{"KNOCKBACK":3}}},"4":{"==":"org.bukkit.inventory.ItemStack","type":"BOW","damage":3,"meta":{"==":"ItemMeta","meta-type":"UNSPECIFIC","enchants":{"ARROW_DAMAGE":1}}},"5":{"==":"org.bukkit.inventory.ItemStack","type":"POTION","damage":16460},"6":{"==":"org.bukkit.inventory.ItemStack","type":"MAP","damage":424},"7":{"==":"org.bukkit.inventory.ItemStack","type":"GOLDEN_APPLE","amount":13},"8":{"==":"org.bukkit.inventory.ItemStack","type":"DIAMOND_HELMET","meta":{"==":"ItemMeta","meta-type":"UNSPECIFIC","enchants":{"PROTECTION_PROJECTILE":3}}},"9":{"==":"org.bukkit.inventory.ItemStack","type":"IRON_CHESTPLATE"},"20":{"==":"org.bukkit.inventory.ItemStack","type":"DIAMOND_LEGGINGS","meta":{"==":"ItemMeta","meta-type":"UNSPECIFIC","enchants":{"PROTECTION_PROJECTILE":3}}},"21":{"==":"org.bukkit.inventory.ItemStack","type":"WOOD","amount":64}},"armorContents":{},"enderChestContents":{},"stats":{"ex":"2.64589","ma":"300","fl":"20","el":"0","hp":"20","xp":"0.0","txp":"0","fd":"0.0","sa":"8.200001","ft":"-20","ra":"300"}}}