{"SURVIVAL":{"enderChestContents":{},"potions":"[]","armorContents":{},"inventoryContents":{"0":{"==":"org.bukkit.inventory.ItemStack","type":"WATCH","meta":{"==":"ItemMeta","meta-type":"UNSPECIFIC","display-name":"§2§lNavigation","lore":["§aRight click with this item","§ain hand to join a server."]}},"1":{"==":"org.bukkit.inventory.ItemStack","type":"INK_SACK","damage":10,"amount":2,"meta":{"==":"ItemMeta","meta-type":"UNSPECIFIC","display-name":"§5§lPlayer Visibility - §aON"}},"2":{"==":"org.bukkit.inventory.ItemStack","type":"BONE","meta":{"==":"ItemMeta","meta-type":"UNSPECIFIC","display-name":"§cAnother Item","lore":["§7If you don't set the permission, the item","§7will be given to everyone. If you don't","§7specify a slot, the item will be in the","§7first empty."]}},"3":{"==":"org.bukkit.inventory.ItemStack","type":"LEAVES"},"4":{"==":"org.bukkit.inventory.ItemStack","type":"ARROW","amount":2},"5":{"==":"org.bukkit.inventory.ItemStack","type":"WHEAT","amount":2},"6":{"==":"org.bukkit.inventory.ItemStack","type":"SEEDS","amount":2},"7":{"==":"org.bukkit.inventory.ItemStack","type":"WOOD"},"8":{"==":"org.bukkit.inventory.ItemStack","type":"WOOD_AXE"}},"stats":{"ex":"0.0","ma":"300","fl":"20","el":"0","xp":"0.0","hp":"20","txp":"0","ft":"-20","sa":"5.0","fd":"0.0","ra":"300"}}}